[{"id":"topology1","devices":[{"type":"capcitor","id":"cap1","name":"capcitorGamd","_default":10.0,"min":0.0,"max":100.0,"netlists":[{"key":"soso","value":"s1"},{"key":"dodo","value":"d1"}]}]},{"id":"toplogogy2","devices":[{"type":"resistor","id":"reseses","name":"resistorGamd","_default":50.0,"min":0.0,"max":1500.0,"netlists":[{"key":"qwe","value":"123"},{"key":"xas","value":"1555"}]},{"type":"capaa","id":"capaa","name":"capapaas23","_default":50.0,"min":0.0,"max":1500.0,"netlists":[{"key":"asdxxxxx","value":"11223"},{"key":"gktgu","value":"123"}]}]}]